{
  "test": "kfold_cv_ols",
  "method": "lm",
  "dataset": "lh",
  "n_folds": 10,
  "n_samples": 48,
  "mean_mse": 235.93858744448855,
  "std_mse": 199.97403613345111,
  "mean_rmse": 13.765292455298914,
  "std_rmse": 7.184498054420857,
  "mean_mae": 13.071294363309935,
  "std_mae": 7.340067740166567,
  "mean_r_squared": -137.3719830383256,
  "std_r_squared": 123.28331851068988,
  "mean_train_r_squared": 0.1156429951339184,
  "fold_results": [
    {
      "fold_index": 1,
      "train_size": 43,
      "test_size": 5,
      "mse": 540.62244799852078,
      "rmse": 23.251289168528285,
      "mae": 23.133878435622101,
      "r_squared": -269.31122399926039,
      "train_r_squared": 0.128769967431183
    },
    {
      "fold_index": 2,
      "train_size": 43,
      "test_size": 5,
      "mse": 267.13869349675554,
      "rmse": 16.34437803945918,
      "mae": 16.199263080324243,
      "r_squared": -132.56934674837777,
      "train_r_squared": 0.08698547821517059
    },
    {
      "fold_index": 3,
      "train_size": 43,
      "test_size": 5,
      "mse": 126.3352082396742,
      "rmse": 11.239893604464154,
      "mae": 10.627370930492438,
      "r_squared": -62.167604119837094,
      "train_r_squared": 0.1003750107498654
    },
    {
      "fold_index": 4,
      "train_size": 43,
      "test_size": 5,
      "mse": 91.697326893258477,
      "rmse": 9.575872121810027,
      "mae": 7.679595278246198,
      "r_squared": -44.848663446629239,
      "train_r_squared": 0.1330049508246945
    },
    {
      "fold_index": 5,
      "train_size": 43,
      "test_size": 5,
      "mse": 12.893550867693911,
      "rmse": 3.59075909351963,
      "mae": 3.043227848101263,
      "r_squared": -5.446775433846955,
      "train_r_squared": 0.1157103159658917
    },
    {
      "fold_index": 6,
      "train_size": 43,
      "test_size": 5,
      "mse": 15.676644475762089,
      "rmse": 3.959374253055916,
      "mae": 3.156296914095083,
      "r_squared": -6.838322237881044,
      "train_r_squared": 0.1116853534171645
    },
    {
      "fold_index": 7,
      "train_size": 43,
      "test_size": 5,
      "mse": 114.02951664684703,
      "rmse": 10.678460406203088,
      "mae": 9.891870028313335,
      "r_squared": -56.014758323423521,
      "train_r_squared": 0.1280696452289653
    },
    {
      "fold_index": 8,
      "train_size": 43,
      "test_size": 5,
      "mse": 510.90284195699661,
      "rmse": 22.603159999367271,
      "mae": 21.050834565814498,
      "r_squared": -254.45142097849831,
      "train_r_squared": 0.2412971972179496
    },
    {
      "fold_index": 9,
      "train_size": 44,
      "test_size": 4,
      "mse": 233.09950439928014,
      "rmse": 15.267596549531957,
      "mae": 14.944323077237176,
      "r_squared": -185.4796035194241,
      "train_r_squared": 0.04399318624069617
    },
    {
      "fold_index": 10,
      "train_size": 44,
      "test_size": 4,
      "mse": 446.99013947009678,
      "rmse": 21.142141317049624,
      "mae": 20.986283474853021,
      "r_squared": -356.5921115760774,
      "train_r_squared": 0.06653884604760323
    }
  ]
}
