{
  "test_name": "Breusch-Godfrey Test (Python - statsmodels)",
  "dataset": "longley",
  "formula": "GNP.deflator ~ GNP + Unemployed + Armed Forces + Population + Year + Employed",
  "order": 1,
  "statistic": 0.11509402820521508,
  "p_value": 0.7344175580660932,
  "test_type": "Chisq",
  "df": [
    1.0
  ],
  "f_statistic": 0.057963970783675524,
  "f_p_value": 0.8157987008164601,
  "f_df": [
    1.0,
    8.0
  ],
  "passed": true,
  "interpretation": "No significant serial correlation detected up to order 1",
  "description": "Tests for serial correlation up to order 1. The LM (Chi-squared) statistic is asymptotically distributed as chi-squared with 1 degrees of freedom. The F statistic provides a finite-sample correction. Uses statsmodels.stats.diagnostic.acorr_breusch_godfrey."
}